{
  "storage_key": "ankara_2026-04-29_high",
  "event_id": "422460",
  "event_slug": "highest-temperature-in-ankara-on-april-29-2026",
  "event_title": "Highest temperature in Ankara on April 29?",
  "city_slug": "ankara",
  "city_name": "Ankara",
  "date": "2026-04-29",
  "unit": "C",
  "station": null,
  "category": null,
  "tags": [
    "Weather",
    "Recurring",
    "Hide From New",
    "Ankara",
    "Daily Temperature",
    "Rewards Automation 100 4.5 50 (1)",
    "Highest temperature"
  ],
  "active": true,
  "closed": true,
  "end_date": "2026-04-29T12:00:00Z",
  "event_end_date": "2026-04-29T12:00:00Z",
  "liquidity": null,
  "volume": 102202.25909800002,
  "market_type": "max_temperature",
  "temperature_metric": "high",
  "all_outcomes": [
    {
      "market_id": "2091615",
      "question": "Will the highest temperature in Ankara be 14°C or below on April 29?",
      "bucket_low": -999.0,
      "bucket_high": 14.0,
      "unit": "C",
      "yes_price": 0.0,
      "no_price": 1.0,
      "volume": 420.2235,
      "liquidity": null,
      "token_id": "56269939403797381833751540460423479136075706328381040495618825623420220055772",
      "outcomes": [
        "Yes",
        "No"
      ],
      "outcome_prices": [
        0.0,
        1.0
      ],
      "active": true,
      "closed": true,
      "raw_source": {
        "market_slug": "highest-temperature-in-ankara-on-april-29-2026-14corbelow",
        "condition_id": "0x8ae6bb0d82342fb477c4dc4bf359835f36bc0e39f3e44c54c7327d8272fa289e"
      }
    },
    {
      "market_id": "2091616",
      "question": "Will the highest temperature in Ankara be 15°C on April 29?",
      "bucket_low": 15.0,
      "bucket_high": 15.0,
      "unit": "C",
      "yes_price": 0.0,
      "no_price": 1.0,
      "volume": 1697.5093680000002,
      "liquidity": null,
      "token_id": "10053076972653720421366205543718114336020001040986197007560911780657787189946",
      "outcomes": [
        "Yes",
        "No"
      ],
      "outcome_prices": [
        0.0,
        1.0
      ],
      "active": true,
      "closed": true,
      "raw_source": {
        "market_slug": "highest-temperature-in-ankara-on-april-29-2026-15c",
        "condition_id": "0x84cbbf245c88b9007d6853a92bcb3b67af9373d96268ef009725e30b30b37e5c"
      }
    },
    {
      "market_id": "2091617",
      "question": "Will the highest temperature in Ankara be 16°C on April 29?",
      "bucket_low": 16.0,
      "bucket_high": 16.0,
      "unit": "C",
      "yes_price": 0.0,
      "no_price": 1.0,
      "volume": 1217.2794319999998,
      "liquidity": null,
      "token_id": "54295821679559515535593856452281263560783197341982605917195697095662906415357",
      "outcomes": [
        "Yes",
        "No"
      ],
      "outcome_prices": [
        0.0,
        1.0
      ],
      "active": true,
      "closed": true,
      "raw_source": {
        "market_slug": "highest-temperature-in-ankara-on-april-29-2026-16c",
        "condition_id": "0x0ac5af2f2013d65d3a18115753669ff935df8c915f7f9230f497fdcf35f7bc8b"
      }
    },
    {
      "market_id": "2091618",
      "question": "Will the highest temperature in Ankara be 17°C on April 29?",
      "bucket_low": 17.0,
      "bucket_high": 17.0,
      "unit": "C",
      "yes_price": 0.0,
      "no_price": 1.0,
      "volume": 13436.356958000002,
      "liquidity": null,
      "token_id": "74221289751351083237371798838810787089948030980930721697097057833734998503846",
      "outcomes": [
        "Yes",
        "No"
      ],
      "outcome_prices": [
        0.0,
        1.0
      ],
      "active": true,
      "closed": true,
      "raw_source": {
        "market_slug": "highest-temperature-in-ankara-on-april-29-2026-17c",
        "condition_id": "0xc9b617c272303809325ccaa55f667eb0641c698410c13495193bd4f3b445530a"
      }
    },
    {
      "market_id": "2091619",
      "question": "Will the highest temperature in Ankara be 18°C on April 29?",
      "bucket_low": 18.0,
      "bucket_high": 18.0,
      "unit": "C",
      "yes_price": 0.0,
      "no_price": 1.0,
      "volume": 8742.820217,
      "liquidity": null,
      "token_id": "78294676849805944306857884980837851565748243162009633824361610414455988067279",
      "outcomes": [
        "Yes",
        "No"
      ],
      "outcome_prices": [
        0.0,
        1.0
      ],
      "active": true,
      "closed": true,
      "raw_source": {
        "market_slug": "highest-temperature-in-ankara-on-april-29-2026-18c",
        "condition_id": "0x341209e481902141feb790bd14535a61024f17d87a3c957124b7ee31b5cd24d2"
      }
    },
    {
      "market_id": "2091620",
      "question": "Will the highest temperature in Ankara be 19°C on April 29?",
      "bucket_low": 19.0,
      "bucket_high": 19.0,
      "unit": "C",
      "yes_price": 0.0,
      "no_price": 1.0,
      "volume": 8000.0493700000015,
      "liquidity": null,
      "token_id": "82759482485255435947002227990006507573645790573765635117104991543911266545801",
      "outcomes": [
        "Yes",
        "No"
      ],
      "outcome_prices": [
        0.0,
        1.0
      ],
      "active": true,
      "closed": true,
      "raw_source": {
        "market_slug": "highest-temperature-in-ankara-on-april-29-2026-19c",
        "condition_id": "0x3e46b45b06f8cb1c5d1928952eb1a97d1d5bd3e3b4118f6316768f0ef8e54945"
      }
    },
    {
      "market_id": "2091621",
      "question": "Will the highest temperature in Ankara be 20°C on April 29?",
      "bucket_low": 20.0,
      "bucket_high": 20.0,
      "unit": "C",
      "yes_price": 1.0,
      "no_price": 0.0,
      "volume": 19461.630596000014,
      "liquidity": null,
      "token_id": "21125059927128209341636594884812474177853125008408252213982475832948315676963",
      "outcomes": [
        "Yes",
        "No"
      ],
      "outcome_prices": [
        1.0,
        0.0
      ],
      "active": true,
      "closed": true,
      "raw_source": {
        "market_slug": "highest-temperature-in-ankara-on-april-29-2026-20c",
        "condition_id": "0x8ee75d2858832cdacdb619dffa1e94663ae16bda3b9212f030a53f84f1e7dfd9"
      }
    },
    {
      "market_id": "2091622",
      "question": "Will the highest temperature in Ankara be 21°C on April 29?",
      "bucket_low": 21.0,
      "bucket_high": 21.0,
      "unit": "C",
      "yes_price": 0.0,
      "no_price": 1.0,
      "volume": 23012.133543,
      "liquidity": null,
      "token_id": "95520458928431490696820210353380053289130286541394807432379492319387323910280",
      "outcomes": [
        "Yes",
        "No"
      ],
      "outcome_prices": [
        0.0,
        1.0
      ],
      "active": true,
      "closed": true,
      "raw_source": {
        "market_slug": "highest-temperature-in-ankara-on-april-29-2026-21c",
        "condition_id": "0x636dbe9806a7eb42992b093ed2b6b8ff7e0e97151eed1812b7d314a93ca8c8d1"
      }
    },
    {
      "market_id": "2091623",
      "question": "Will the highest temperature in Ankara be 22°C on April 29?",
      "bucket_low": 22.0,
      "bucket_high": 22.0,
      "unit": "C",
      "yes_price": 0.0,
      "no_price": 1.0,
      "volume": 13761.329696999992,
      "liquidity": null,
      "token_id": "24182259842790888961065469777283797714562328488053319450101639287303495104430",
      "outcomes": [
        "Yes",
        "No"
      ],
      "outcome_prices": [
        0.0,
        1.0
      ],
      "active": true,
      "closed": true,
      "raw_source": {
        "market_slug": "highest-temperature-in-ankara-on-april-29-2026-22c",
        "condition_id": "0x769e29e0c8946641585383569e7a26fb09405eaeeaa8c6be0e78f814dd76f0f6"
      }
    },
    {
      "market_id": "2091624",
      "question": "Will the highest temperature in Ankara be 23°C on April 29?",
      "bucket_low": 23.0,
      "bucket_high": 23.0,
      "unit": "C",
      "yes_price": 0.0,
      "no_price": 1.0,
      "volume": 5357.241163000005,
      "liquidity": null,
      "token_id": "82365244923930909507993283683194135107064987639412252958795794007000089990595",
      "outcomes": [
        "Yes",
        "No"
      ],
      "outcome_prices": [
        0.0,
        1.0
      ],
      "active": true,
      "closed": true,
      "raw_source": {
        "market_slug": "highest-temperature-in-ankara-on-april-29-2026-23c",
        "condition_id": "0x029754613b7d9118140ea0910561e13ab74476ef19e6df1092827d0b8aea5e5b"
      }
    },
    {
      "market_id": "2091625",
      "question": "Will the highest temperature in Ankara be 24°C or higher on April 29?",
      "bucket_low": 24.0,
      "bucket_high": 999.0,
      "unit": "C",
      "yes_price": 0.0,
      "no_price": 1.0,
      "volume": 7095.685254000005,
      "liquidity": null,
      "token_id": "3327744143524587200333948217315198350726496562464397545777052255131757616767",
      "outcomes": [
        "Yes",
        "No"
      ],
      "outcome_prices": [
        0.0,
        1.0
      ],
      "active": true,
      "closed": true,
      "raw_source": {
        "market_slug": "highest-temperature-in-ankara-on-april-29-2026-24corhigher",
        "condition_id": "0x51045f56abf84d2ee466254d9add6ccd6f2744e2b19a610182cef5fce2ec95e5"
      }
    }
  ],
  "market_snapshots": [
    {
      "ts": "2026-06-07T16:06:03.125314+00:00",
      "active": true,
      "closed": true,
      "end_date": "2026-04-29T12:00:00Z",
      "liquidity": null,
      "volume": 102202.25909800002,
      "outcomes_count": 11,
      "top_bucket": "20.0-20.0C",
      "top_price": 1.0,
      "event_title": "Highest temperature in Ankara on April 29?"
    }
  ],
  "settle_at": "2026-04-29T21:00:00+00:00",
  "hours_to_settle": -931.1,
  "raw_source": {
    "event_slug": "highest-temperature-in-ankara-on-april-29-2026",
    "event_id": "422460",
    "markets_count": 11,
    "game_start_time": "2026-04-28 21:00:00+00"
  },
  "status": "inactive",
  "discovery_source": "gamma_history_sync",
  "hours_at_discovery": 0.0,
  "first_seen_at": "2026-06-07T16:06:03.125314+00:00",
  "last_seen_at": "2026-06-07T16:06:03.125314+00:00",
  "last_refreshed_at": "2026-06-07T16:06:03.125314+00:00",
  "created_at": "2026-06-07T16:06:03.125314+00:00",
  "updated_at": "2026-06-10T18:47:48.300009+00:00",
  "forecast_snapshots": [],
  "raw_payload_ref": "data\\raw\\gamma_events_raw.json",
  "extensions": {
    "winning_bucket": {
      "winning_bucket": "20C",
      "resolved_value": "20C",
      "resolution_source": null,
      "winning_market_id": "2091621",
      "winning_question": "Will the highest temperature in Ankara be 20°C on April 29?"
    },
    "gamma_enriched_at": "2026-06-07T16:06:03.127319+00:00",
    "history_forecasts": {
      "saved_at": "2026-06-10T18:47:48.300009+00:00",
      "single": {
        "city_slug": "ankara",
        "date": "2026-04-29",
        "metric": "high",
        "model": "ecmwf_ifs",
        "requested_model": null,
        "model_fallback": false,
        "unit": null,
        "temp": null,
        "error": "forecast_unavailable"
      },
      "ensemble": {
        "city_slug": "ankara",
        "date": "2026-04-29",
        "metric": "high",
        "model": "ecmwf_ifs025_ensemble+ncep_gefs_seamless",
        "requested_model": "ecmwf_ifs025_ensemble+ncep_gefs_seamless",
        "model_fallback": false,
        "unit": "C",
        "temp": 17.2,
        "error": null,
        "models_temps": [
          {
            "model": "ecmwf_ifs025_ensemble",
            "temp": 17.2,
            "error": null
          },
          {
            "model": "ncep_gefs_seamless",
            "temp": 16.5,
            "error": null
          }
        ]
      }
    }
  },
  "legacy": null
}