{
  "storage_key": "austin_2026-04-30_high",
  "event_id": "426256",
  "event_slug": "highest-temperature-in-austin-on-april-30-2026",
  "event_title": "Highest temperature in Austin on April 30?",
  "city_slug": "austin",
  "city_name": "Austin",
  "date": "2026-04-30",
  "unit": "F",
  "station": null,
  "category": null,
  "tags": [
    "Weather",
    "Recurring",
    "Hide From New",
    "Daily Temperature",
    "Austin",
    "Rewards Automation 50 4.5 50",
    "Highest temperature"
  ],
  "active": true,
  "closed": true,
  "end_date": "2026-04-30T12:00:00Z",
  "event_end_date": "2026-04-30T12:00:00Z",
  "liquidity": null,
  "volume": 43436.89574500001,
  "market_type": "max_temperature",
  "temperature_metric": "high",
  "all_outcomes": [
    {
      "market_id": "2102412",
      "question": "Will the highest temperature in Austin be 73°F or below on April 30?",
      "bucket_low": -999.0,
      "bucket_high": 73.0,
      "unit": "F",
      "yes_price": 1.0,
      "no_price": 0.0,
      "volume": 7416.431153000006,
      "liquidity": null,
      "token_id": "23817342785062363886414885824051413929474549865476961527957656078322583268324",
      "outcomes": [
        "Yes",
        "No"
      ],
      "outcome_prices": [
        1.0,
        0.0
      ],
      "active": true,
      "closed": true,
      "raw_source": {
        "market_slug": "highest-temperature-in-austin-on-april-30-2026-73forbelow",
        "condition_id": "0xa04ce9af0e1ce32260a63ff01120007714128540659cef9e299c7d89d59cc833"
      }
    },
    {
      "market_id": "2102413",
      "question": "Will the highest temperature in Austin be between 74-75°F on April 30?",
      "bucket_low": 74.0,
      "bucket_high": 75.0,
      "unit": "F",
      "yes_price": 0.0,
      "no_price": 1.0,
      "volume": 4151.056791,
      "liquidity": null,
      "token_id": "55221343604929967907813497027711300745568740159764979861817819884765246338855",
      "outcomes": [
        "Yes",
        "No"
      ],
      "outcome_prices": [
        0.0,
        1.0
      ],
      "active": true,
      "closed": true,
      "raw_source": {
        "market_slug": "highest-temperature-in-austin-on-april-30-2026-74-75f",
        "condition_id": "0x2c33d6401ab0dfb60e803a96082e76fb07f457f8eb84888f820f8bae225c8016"
      }
    },
    {
      "market_id": "2102414",
      "question": "Will the highest temperature in Austin be between 76-77°F on April 30?",
      "bucket_low": 76.0,
      "bucket_high": 77.0,
      "unit": "F",
      "yes_price": 0.0,
      "no_price": 1.0,
      "volume": 4412.775792999999,
      "liquidity": null,
      "token_id": "34073056872177422891898307730001813409599408487363591258855237855665151652707",
      "outcomes": [
        "Yes",
        "No"
      ],
      "outcome_prices": [
        0.0,
        1.0
      ],
      "active": true,
      "closed": true,
      "raw_source": {
        "market_slug": "highest-temperature-in-austin-on-april-30-2026-76-77f",
        "condition_id": "0xa6aa17ae5c806fc1215f34ed279629f274054d6a369776db5172e207a9d10286"
      }
    },
    {
      "market_id": "2102415",
      "question": "Will the highest temperature in Austin be between 78-79°F on April 30?",
      "bucket_low": 78.0,
      "bucket_high": 79.0,
      "unit": "F",
      "yes_price": 0.0,
      "no_price": 1.0,
      "volume": 6854.837384,
      "liquidity": null,
      "token_id": "1492154060483519068088593050606679436692820782166846234315153460771132947235",
      "outcomes": [
        "Yes",
        "No"
      ],
      "outcome_prices": [
        0.0,
        1.0
      ],
      "active": true,
      "closed": true,
      "raw_source": {
        "market_slug": "highest-temperature-in-austin-on-april-30-2026-78-79f",
        "condition_id": "0xeba681065d24270269ae41443e58321280b43553c553e6336f94710322bc60a9"
      }
    },
    {
      "market_id": "2102416",
      "question": "Will the highest temperature in Austin be between 80-81°F on April 30?",
      "bucket_low": 80.0,
      "bucket_high": 81.0,
      "unit": "F",
      "yes_price": 0.0,
      "no_price": 1.0,
      "volume": 4973.222231,
      "liquidity": null,
      "token_id": "50081994240519641336814665031875203226353712270770100695194307286116468137665",
      "outcomes": [
        "Yes",
        "No"
      ],
      "outcome_prices": [
        0.0,
        1.0
      ],
      "active": true,
      "closed": true,
      "raw_source": {
        "market_slug": "highest-temperature-in-austin-on-april-30-2026-80-81f",
        "condition_id": "0xe45069b64e1827cc3ece137206c07c232ebe49d84dccf8da3f47764c393effbf"
      }
    },
    {
      "market_id": "2102417",
      "question": "Will the highest temperature in Austin be between 82-83°F on April 30?",
      "bucket_low": 82.0,
      "bucket_high": 83.0,
      "unit": "F",
      "yes_price": 0.0,
      "no_price": 1.0,
      "volume": 6063.889048000002,
      "liquidity": null,
      "token_id": "66842875592615959124614729803092223701877626992761372425740901155833878182211",
      "outcomes": [
        "Yes",
        "No"
      ],
      "outcome_prices": [
        0.0,
        1.0
      ],
      "active": true,
      "closed": true,
      "raw_source": {
        "market_slug": "highest-temperature-in-austin-on-april-30-2026-82-83f",
        "condition_id": "0x81baef24264f86e9c12bb41f6b6a8f1bbe61750ffba1facc0df9c08ca08a5d7a"
      }
    },
    {
      "market_id": "2102418",
      "question": "Will the highest temperature in Austin be between 84-85°F on April 30?",
      "bucket_low": 84.0,
      "bucket_high": 85.0,
      "unit": "F",
      "yes_price": 0.0,
      "no_price": 1.0,
      "volume": 2436.708807,
      "liquidity": null,
      "token_id": "65923053001180296284562683200004023781230234244961244058860374515850502184137",
      "outcomes": [
        "Yes",
        "No"
      ],
      "outcome_prices": [
        0.0,
        1.0
      ],
      "active": true,
      "closed": true,
      "raw_source": {
        "market_slug": "highest-temperature-in-austin-on-april-30-2026-84-85f",
        "condition_id": "0xbfd4408d39abe6d4e5627195caf1ee044e841dee96dd850316560f0c63882543"
      }
    },
    {
      "market_id": "2102419",
      "question": "Will the highest temperature in Austin be between 86-87°F on April 30?",
      "bucket_low": 86.0,
      "bucket_high": 87.0,
      "unit": "F",
      "yes_price": 0.0,
      "no_price": 1.0,
      "volume": 2133.955,
      "liquidity": null,
      "token_id": "115549276331764568387991422044035471218320708550937308185215529405806379996382",
      "outcomes": [
        "Yes",
        "No"
      ],
      "outcome_prices": [
        0.0,
        1.0
      ],
      "active": true,
      "closed": true,
      "raw_source": {
        "market_slug": "highest-temperature-in-austin-on-april-30-2026-86-87f",
        "condition_id": "0x7be7ed8ac06727ddae42e2a1547db5471bf71c9e5ced9c1b92d170fc2be675df"
      }
    },
    {
      "market_id": "2102420",
      "question": "Will the highest temperature in Austin be between 88-89°F on April 30?",
      "bucket_low": 88.0,
      "bucket_high": 89.0,
      "unit": "F",
      "yes_price": 0.0,
      "no_price": 1.0,
      "volume": 1434.1320999999998,
      "liquidity": null,
      "token_id": "18657566686437158772030998135371575190750796244053807672224688871996648578496",
      "outcomes": [
        "Yes",
        "No"
      ],
      "outcome_prices": [
        0.0,
        1.0
      ],
      "active": true,
      "closed": true,
      "raw_source": {
        "market_slug": "highest-temperature-in-austin-on-april-30-2026-88-89f",
        "condition_id": "0xc7797ef8952d031dcc0dfdc950ce06af085391ce3607b72f5f15baa82c4de57d"
      }
    },
    {
      "market_id": "2102421",
      "question": "Will the highest temperature in Austin be between 90-91°F on April 30?",
      "bucket_low": 90.0,
      "bucket_high": 91.0,
      "unit": "F",
      "yes_price": 0.0,
      "no_price": 1.0,
      "volume": 1173.0074849999996,
      "liquidity": null,
      "token_id": "9126238506563623542719127482076742612737819841446250976756625899502712427787",
      "outcomes": [
        "Yes",
        "No"
      ],
      "outcome_prices": [
        0.0,
        1.0
      ],
      "active": true,
      "closed": true,
      "raw_source": {
        "market_slug": "highest-temperature-in-austin-on-april-30-2026-90-91f",
        "condition_id": "0x016e0da09c7306e6bfde4d815a5f22b9ca97341dd2c1bad0cb69060f7a33fb87"
      }
    },
    {
      "market_id": "2102422",
      "question": "Will the highest temperature in Austin be 92°F or higher on April 30?",
      "bucket_low": 92.0,
      "bucket_high": 999.0,
      "unit": "F",
      "yes_price": 0.0,
      "no_price": 1.0,
      "volume": 2386.8799530000006,
      "liquidity": null,
      "token_id": "36742261518076998693441781221147316261607021925428157609240991815187577361949",
      "outcomes": [
        "Yes",
        "No"
      ],
      "outcome_prices": [
        0.0,
        1.0
      ],
      "active": true,
      "closed": true,
      "raw_source": {
        "market_slug": "highest-temperature-in-austin-on-april-30-2026-92forhigher",
        "condition_id": "0x95ee7911c0f327a03b7f6e1d26067454b28abfaa0292e534919a7629caf6795e"
      }
    }
  ],
  "market_snapshots": [
    {
      "ts": "2026-06-07T16:06:02.847589+00:00",
      "active": true,
      "closed": true,
      "end_date": "2026-04-30T12:00:00Z",
      "liquidity": null,
      "volume": 43436.89574500001,
      "outcomes_count": 11,
      "top_bucket": "<=73.0F",
      "top_price": 1.0,
      "event_title": "Highest temperature in Austin on April 30?"
    }
  ],
  "settle_at": "2026-05-01T05:00:00+00:00",
  "hours_to_settle": -899.1,
  "raw_source": {
    "event_slug": "highest-temperature-in-austin-on-april-30-2026",
    "event_id": "426256",
    "markets_count": 11,
    "game_start_time": "2026-04-30 05:00:00+00"
  },
  "status": "inactive",
  "discovery_source": "gamma_history_sync",
  "hours_at_discovery": 0.0,
  "first_seen_at": "2026-06-07T16:06:02.847589+00:00",
  "last_seen_at": "2026-06-07T16:06:02.847589+00:00",
  "last_refreshed_at": "2026-06-07T16:06:02.847589+00:00",
  "created_at": "2026-06-07T16:06:02.847589+00:00",
  "updated_at": "2026-06-10T17:17:28.442782+00:00",
  "forecast_snapshots": [],
  "raw_payload_ref": "data\\raw\\gamma_events_raw.json",
  "extensions": {
    "winning_bucket": {
      "winning_bucket": "<=73F",
      "resolved_value": "<=73F",
      "resolution_source": null,
      "winning_market_id": "2102412",
      "winning_question": "Will the highest temperature in Austin be 73°F or below on April 30?"
    },
    "gamma_enriched_at": "2026-06-07T16:06:02.848610+00:00"
  },
  "legacy": null
}