{
  "storage_key": "chicago_2026-01-30_high",
  "event_id": "191142",
  "event_slug": "highest-temperature-in-chicago-on-january-30",
  "event_title": "Highest temperature in Chicago on January 30?",
  "city_slug": "chicago",
  "city_name": "Chicago",
  "date": "2026-01-30",
  "unit": "F",
  "station": null,
  "category": null,
  "tags": [
    "Weather",
    "Recurring",
    "Hide From New",
    "Chicago"
  ],
  "active": true,
  "closed": true,
  "end_date": "2026-01-30T12:00:00Z",
  "event_end_date": "2026-01-30T12:00:00Z",
  "liquidity": null,
  "volume": 26248.034332,
  "market_type": "max_temperature",
  "temperature_metric": "high",
  "all_outcomes": [
    {
      "market_id": "1282093",
      "question": "Will the highest temperature in Chicago be 13°F or below on January 30?",
      "bucket_low": -999.0,
      "bucket_high": 13.0,
      "unit": "F",
      "yes_price": 0.0,
      "no_price": 1.0,
      "volume": 5347.702603,
      "liquidity": null,
      "token_id": "85209759589926767860616254910948335165228582707950003216238560793812997515432",
      "outcomes": [
        "Yes",
        "No"
      ],
      "outcome_prices": [
        0.0,
        1.0
      ],
      "active": true,
      "closed": true,
      "raw_source": {
        "market_slug": "highest-temperature-in-chicago-on-january-30-13forbelow",
        "condition_id": "0xf01352d941b4eae3fb00dfbaf06654a641a29502d609d83d4db73e464700a3b9"
      }
    },
    {
      "market_id": "1282094",
      "question": "Will the highest temperature in Chicago be between 14-15°F on January 30?",
      "bucket_low": 14.0,
      "bucket_high": 15.0,
      "unit": "F",
      "yes_price": 0.0,
      "no_price": 1.0,
      "volume": 4029.046149,
      "liquidity": null,
      "token_id": "21142496247054476219726089620137212256951912411292914694811480523231706275404",
      "outcomes": [
        "Yes",
        "No"
      ],
      "outcome_prices": [
        0.0,
        1.0
      ],
      "active": true,
      "closed": true,
      "raw_source": {
        "market_slug": "highest-temperature-in-chicago-on-january-30-14-15f",
        "condition_id": "0xde2f9295691d81d61162322dd7a2df55831b9e94cb4332502f56b93b6462eef7"
      }
    },
    {
      "market_id": "1282095",
      "question": "Will the highest temperature in Chicago be between 16-17°F on January 30?",
      "bucket_low": 16.0,
      "bucket_high": 17.0,
      "unit": "F",
      "yes_price": 0.0,
      "no_price": 1.0,
      "volume": 2913.483714,
      "liquidity": null,
      "token_id": "90698233428833450378083456926875283186766485371136820622319028513972382287617",
      "outcomes": [
        "Yes",
        "No"
      ],
      "outcome_prices": [
        0.0,
        1.0
      ],
      "active": true,
      "closed": true,
      "raw_source": {
        "market_slug": "highest-temperature-in-chicago-on-january-30-16-17f",
        "condition_id": "0x2fcd950815d717479998b2b98e85d21398c3a8cefc8f70b0c3ed1f678685cc2a"
      }
    },
    {
      "market_id": "1282096",
      "question": "Will the highest temperature in Chicago be between 18-19°F on January 30?",
      "bucket_low": 18.0,
      "bucket_high": 19.0,
      "unit": "F",
      "yes_price": 1.0,
      "no_price": 0.0,
      "volume": 3280.620257,
      "liquidity": null,
      "token_id": "10328585135727030341819763794978982603982211728105870672599126409073092237258",
      "outcomes": [
        "Yes",
        "No"
      ],
      "outcome_prices": [
        1.0,
        0.0
      ],
      "active": true,
      "closed": true,
      "raw_source": {
        "market_slug": "highest-temperature-in-chicago-on-january-30-18-19f",
        "condition_id": "0xbe9a2b6c7d81227651e3e4e7e5e888a306683387b7ab87678b24c9a9d7654238"
      }
    },
    {
      "market_id": "1282097",
      "question": "Will the highest temperature in Chicago be between 20-21°F on January 30?",
      "bucket_low": 20.0,
      "bucket_high": 21.0,
      "unit": "F",
      "yes_price": 0.0,
      "no_price": 1.0,
      "volume": 3966.011383,
      "liquidity": null,
      "token_id": "102789432456446131426040323123530597945473985448840454532252546253290982047985",
      "outcomes": [
        "Yes",
        "No"
      ],
      "outcome_prices": [
        0.0,
        1.0
      ],
      "active": true,
      "closed": true,
      "raw_source": {
        "market_slug": "highest-temperature-in-chicago-on-january-30-20-21f",
        "condition_id": "0xc1ad32761070f90633c62533ff4f249e255fba380db90f3bbb9359c1e252b5e0"
      }
    },
    {
      "market_id": "1282098",
      "question": "Will the highest temperature in Chicago be between 22-23°F on January 30?",
      "bucket_low": 22.0,
      "bucket_high": 23.0,
      "unit": "F",
      "yes_price": 0.0,
      "no_price": 1.0,
      "volume": 4623.625948,
      "liquidity": null,
      "token_id": "42993504209166289402917419630700781815367112036390717164713113586659191750158",
      "outcomes": [
        "Yes",
        "No"
      ],
      "outcome_prices": [
        0.0,
        1.0
      ],
      "active": true,
      "closed": true,
      "raw_source": {
        "market_slug": "highest-temperature-in-chicago-on-january-30-22-23f",
        "condition_id": "0x88c2f23407408cc3c3ec5a45e2e10eb27b308796baa8a0fa09de8a3c8a218078"
      }
    },
    {
      "market_id": "1282099",
      "question": "Will the highest temperature in Chicago be 24°F or higher on January 30?",
      "bucket_low": 24.0,
      "bucket_high": 999.0,
      "unit": "F",
      "yes_price": 0.0,
      "no_price": 1.0,
      "volume": 2087.544278,
      "liquidity": null,
      "token_id": "49319555149954171188176607212857802166635628006696665543590560867678684319943",
      "outcomes": [
        "Yes",
        "No"
      ],
      "outcome_prices": [
        0.0,
        1.0
      ],
      "active": true,
      "closed": true,
      "raw_source": {
        "market_slug": "highest-temperature-in-chicago-on-january-30-24forhigher",
        "condition_id": "0x81116a724a54aaa6fd806e2bdbd2ac7049361aaf7dcd750d62e3d89250d005e0"
      }
    }
  ],
  "market_snapshots": [
    {
      "ts": "2026-06-07T16:06:12.269155+00:00",
      "active": true,
      "closed": true,
      "end_date": "2026-01-30T12:00:00Z",
      "liquidity": null,
      "volume": 26248.034332,
      "outcomes_count": 7,
      "top_bucket": "18.0-19.0F",
      "top_price": 1.0,
      "event_title": "Highest temperature in Chicago on January 30?"
    }
  ],
  "settle_at": "2026-01-31T06:00:00+00:00",
  "hours_to_settle": -3058.1,
  "raw_source": {
    "event_slug": "highest-temperature-in-chicago-on-january-30",
    "event_id": "191142",
    "markets_count": 7,
    "game_start_time": null
  },
  "status": "inactive",
  "discovery_source": "gamma_history_sync",
  "hours_at_discovery": 0.0,
  "first_seen_at": "2026-06-07T16:06:12.269155+00:00",
  "last_seen_at": "2026-06-07T16:06:12.269155+00:00",
  "last_refreshed_at": "2026-06-07T16:06:12.269155+00:00",
  "created_at": "2026-06-07T16:06:12.269155+00:00",
  "updated_at": "2026-06-10T17:17:28.737592+00:00",
  "forecast_snapshots": [],
  "raw_payload_ref": "data\\raw\\gamma_events_raw.json",
  "extensions": {
    "winning_bucket": {
      "winning_bucket": "18-19F",
      "resolved_value": "18-19F",
      "resolution_source": null,
      "winning_market_id": "1282096",
      "winning_question": "Will the highest temperature in Chicago be between 18-19°F on January 30?"
    },
    "gamma_enriched_at": "2026-06-07T16:06:12.270159+00:00"
  },
  "legacy": null
}