{
  "storage_key": "houston_2026-06-09_high",
  "event_id": "571032",
  "event_slug": "highest-temperature-in-houston-on-june-9-2026",
  "event_title": "Highest temperature in Houston on June 9?",
  "city_slug": "houston",
  "city_name": "Houston",
  "date": "2026-06-09",
  "unit": "F",
  "station": null,
  "category": null,
  "tags": [
    "Weather",
    "Recurring",
    "Hide From New",
    "Daily Temperature",
    "Houston",
    "Rewards Automation 100 4.5 50 (2)",
    "Highest temperature"
  ],
  "active": true,
  "closed": false,
  "end_date": "2026-06-09T12:00:00Z",
  "event_end_date": "2026-06-09T12:00:00Z",
  "liquidity": 57784.00289,
  "volume": 12843.392211999999,
  "market_type": "max_temperature",
  "temperature_metric": "high",
  "all_outcomes": [
    {
      "market_id": "2466935",
      "question": "Will the highest temperature in Houston be 79°F or below on June 9?",
      "bucket_low": -999.0,
      "bucket_high": 79.0,
      "unit": "F",
      "yes_price": 0.0005,
      "no_price": 0.9995,
      "volume": 461.884057,
      "liquidity": 12421.23265,
      "token_id": "34889287992067653536944656136658956850626146067061908015351528020706003927852",
      "outcomes": [
        "Yes",
        "No"
      ],
      "outcome_prices": [
        0.0005,
        0.9995
      ],
      "active": true,
      "closed": false,
      "raw_source": {
        "market_slug": "highest-temperature-in-houston-on-june-9-2026-79forbelow",
        "condition_id": "0x68cdfe6fd462145e1e056112a124c00d42aea4d5e1bf7c5c3ac77cc9aca3319c"
      }
    },
    {
      "market_id": "2466936",
      "question": "Will the highest temperature in Houston be between 80-81°F on June 9?",
      "bucket_low": 80.0,
      "bucket_high": 81.0,
      "unit": "F",
      "yes_price": 0.0005,
      "no_price": 0.9995,
      "volume": 748.229492,
      "liquidity": 10504.16754,
      "token_id": "67403153454928676169255440754424332616009432640813838613575783656613934089983",
      "outcomes": [
        "Yes",
        "No"
      ],
      "outcome_prices": [
        0.0005,
        0.9995
      ],
      "active": true,
      "closed": false,
      "raw_source": {
        "market_slug": "highest-temperature-in-houston-on-june-9-2026-80-81f",
        "condition_id": "0x9ad2129bec53efb691cbfc949baad5306459c40c009a4414a2b4c2b20190ba71"
      }
    },
    {
      "market_id": "2466937",
      "question": "Will the highest temperature in Houston be between 82-83°F on June 9?",
      "bucket_low": 82.0,
      "bucket_high": 83.0,
      "unit": "F",
      "yes_price": 0.0005,
      "no_price": 0.9995,
      "volume": 795.8936379999999,
      "liquidity": 10525.47732,
      "token_id": "54405078805007362121564145662137050050377474310272808870395505289171814622497",
      "outcomes": [
        "Yes",
        "No"
      ],
      "outcome_prices": [
        0.0005,
        0.9995
      ],
      "active": true,
      "closed": false,
      "raw_source": {
        "market_slug": "highest-temperature-in-houston-on-june-9-2026-82-83f",
        "condition_id": "0x6be3a1414e7772eb6a86ff4b515c398fdbb003a6231b424c08c579e9edef40b2"
      }
    },
    {
      "market_id": "2466938",
      "question": "Will the highest temperature in Houston be between 84-85°F on June 9?",
      "bucket_low": 84.0,
      "bucket_high": 85.0,
      "unit": "F",
      "yes_price": 0.0005,
      "no_price": 0.9995,
      "volume": 2225.9611499999996,
      "liquidity": 9406.76905,
      "token_id": "44465502735887911088085235750684468106697126815042027075972364529861643611046",
      "outcomes": [
        "Yes",
        "No"
      ],
      "outcome_prices": [
        0.0005,
        0.9995
      ],
      "active": true,
      "closed": false,
      "raw_source": {
        "market_slug": "highest-temperature-in-houston-on-june-9-2026-84-85f",
        "condition_id": "0x66de9f264f3260870de637ad47d361f8dd384ff004ec973da2a1173f72e97d91"
      }
    },
    {
      "market_id": "2466939",
      "question": "Will the highest temperature in Houston be between 86-87°F on June 9?",
      "bucket_low": 86.0,
      "bucket_high": 87.0,
      "unit": "F",
      "yes_price": 0.0005,
      "no_price": 0.9995,
      "volume": 2749.168032,
      "liquidity": 8474.15292,
      "token_id": "1560000825051125695380774186867923014387483553048085602395301337014148312907",
      "outcomes": [
        "Yes",
        "No"
      ],
      "outcome_prices": [
        0.0005,
        0.9995
      ],
      "active": true,
      "closed": false,
      "raw_source": {
        "market_slug": "highest-temperature-in-houston-on-june-9-2026-86-87f",
        "condition_id": "0x1aafc9afb6312879f2b181a2c24d61b2a9224f8f77556274ae485704e3657fc5"
      }
    },
    {
      "market_id": "2466940",
      "question": "Will the highest temperature in Houston be between 88-89°F on June 9?",
      "bucket_low": 88.0,
      "bucket_high": 89.0,
      "unit": "F",
      "yes_price": 0.245,
      "no_price": 0.755,
      "volume": 1026.3791219999998,
      "liquidity": 145.7261,
      "token_id": "39040986662975884071615530461425410797150971974862353123310139923222691118065",
      "outcomes": [
        "Yes",
        "No"
      ],
      "outcome_prices": [
        0.245,
        0.755
      ],
      "active": true,
      "closed": false,
      "raw_source": {
        "market_slug": "highest-temperature-in-houston-on-june-9-2026-88-89f",
        "condition_id": "0x75d809710820897736b7de199466da3cfff1d1a97fbbbc67a777af85a0fcc7a6"
      }
    },
    {
      "market_id": "2466941",
      "question": "Will the highest temperature in Houston be between 90-91°F on June 9?",
      "bucket_low": 90.0,
      "bucket_high": 91.0,
      "unit": "F",
      "yes_price": 0.7,
      "no_price": 0.3,
      "volume": 1384.9778819999997,
      "liquidity": 153.99,
      "token_id": "1427086148483430381705060411941649638454550056904039511218073300527150123051",
      "outcomes": [
        "Yes",
        "No"
      ],
      "outcome_prices": [
        0.7,
        0.3
      ],
      "active": true,
      "closed": false,
      "raw_source": {
        "market_slug": "highest-temperature-in-houston-on-june-9-2026-90-91f",
        "condition_id": "0xefa4bf41415c78703707f82066f3d275d3495f0b6f13cdc8c992e317c55582f8"
      }
    },
    {
      "market_id": "2466942",
      "question": "Will the highest temperature in Houston be between 92-93°F on June 9?",
      "bucket_low": 92.0,
      "bucket_high": 93.0,
      "unit": "F",
      "yes_price": 0.0125,
      "no_price": 0.9875,
      "volume": 995.567019,
      "liquidity": 340.66547,
      "token_id": "45144589348266029223772275938107689974574052711915691379037502157349622428948",
      "outcomes": [
        "Yes",
        "No"
      ],
      "outcome_prices": [
        0.0125,
        0.9875
      ],
      "active": true,
      "closed": false,
      "raw_source": {
        "market_slug": "highest-temperature-in-houston-on-june-9-2026-92-93f",
        "condition_id": "0x29d938f4972ad66213e27b169c232fce8dddc103b907a622feef4f1355a46f8f"
      }
    },
    {
      "market_id": "2466943",
      "question": "Will the highest temperature in Houston be between 94-95°F on June 9?",
      "bucket_low": 94.0,
      "bucket_high": 95.0,
      "unit": "F",
      "yes_price": 0.014,
      "no_price": 0.986,
      "volume": 668.924519,
      "liquidity": 1200.75396,
      "token_id": "106486655640741930689755611227639049090428249331232549241629977539633756395347",
      "outcomes": [
        "Yes",
        "No"
      ],
      "outcome_prices": [
        0.014,
        0.986
      ],
      "active": true,
      "closed": false,
      "raw_source": {
        "market_slug": "highest-temperature-in-houston-on-june-9-2026-94-95f",
        "condition_id": "0x2bdda15ed4126fe02a5d683a3b11cc72c709902e763f3f83d312bf482d6c60c5"
      }
    },
    {
      "market_id": "2466944",
      "question": "Will the highest temperature in Houston be between 96-97°F on June 9?",
      "bucket_low": 96.0,
      "bucket_high": 97.0,
      "unit": "F",
      "yes_price": 0.005,
      "no_price": 0.995,
      "volume": 1698.9438630000002,
      "liquidity": 1125.06684,
      "token_id": "89581514072424761899021721325695296865299793099991045067573100010489738267859",
      "outcomes": [
        "Yes",
        "No"
      ],
      "outcome_prices": [
        0.005,
        0.995
      ],
      "active": true,
      "closed": false,
      "raw_source": {
        "market_slug": "highest-temperature-in-houston-on-june-9-2026-96-97f",
        "condition_id": "0xf8dcbe1bd0bf801e82671028ef4f0744ecc4b733ca38283ea191008347e24f70"
      }
    },
    {
      "market_id": "2466945",
      "question": "Will the highest temperature in Houston be 98°F or higher on June 9?",
      "bucket_low": 98.0,
      "bucket_high": 999.0,
      "unit": "F",
      "yes_price": 0.0025,
      "no_price": 0.9975,
      "volume": 264.0386,
      "liquidity": 2833.42433,
      "token_id": "107300386224356836665342370457209876397675670911929769849740791995762143567629",
      "outcomes": [
        "Yes",
        "No"
      ],
      "outcome_prices": [
        0.0025,
        0.9975
      ],
      "active": true,
      "closed": false,
      "raw_source": {
        "market_slug": "highest-temperature-in-houston-on-june-9-2026-98forhigher",
        "condition_id": "0x0d582edf21747297d8deef4d27c77cf47e69fdcae4081bdf3ff5f9039c028623"
      }
    }
  ],
  "market_snapshots": [
    {
      "ts": "2026-06-09T18:59:59.294063+00:00",
      "active": true,
      "closed": false,
      "end_date": "2026-06-09T12:00:00Z",
      "liquidity": 57784.00289,
      "volume": 12843.392211999999,
      "outcomes_count": 11,
      "top_bucket": "90.0-91.0F",
      "top_price": 0.7,
      "event_title": "Highest temperature in Houston on June 9?"
    }
  ],
  "settle_at": "2026-06-10T05:00:00+00:00",
  "hours_to_settle": 10.0,
  "raw_source": {
    "event_slug": "highest-temperature-in-houston-on-june-9-2026",
    "event_id": "571032",
    "markets_count": 11,
    "game_start_time": "2026-06-09 05:00:00+00"
  },
  "status": "inactive",
  "discovery_source": "combined",
  "hours_at_discovery": 0.0,
  "first_seen_at": "2026-06-08T09:41:19.373289+00:00",
  "last_seen_at": "2026-06-09T18:59:59.294063+00:00",
  "last_refreshed_at": "2026-06-09T18:59:59.294063+00:00",
  "created_at": "2026-06-08T09:41:19.373289+00:00",
  "updated_at": "2026-06-10T17:17:29.209691+00:00",
  "forecast_snapshots": [],
  "raw_payload_ref": "data\\raw\\gamma_events_raw.json",
  "extensions": {},
  "legacy": null
}