{
  "storage_key": "shanghai_2026-05-27_high",
  "event_id": "522322",
  "event_slug": "highest-temperature-in-shanghai-on-may-27-2026",
  "event_title": "Highest temperature in Shanghai on May 27?",
  "city_slug": "shanghai",
  "city_name": "Shanghai",
  "date": "2026-05-27",
  "unit": "C",
  "station": null,
  "category": null,
  "tags": [
    "Weather",
    "Recurring",
    "Hide From New",
    "Daily Temperature",
    "Shanghai",
    "Rewards Automation 100 4.5 50 (1)",
    "Highest temperature"
  ],
  "active": true,
  "closed": true,
  "end_date": "2026-05-27T12:00:00Z",
  "event_end_date": "2026-05-27T12:00:00Z",
  "liquidity": null,
  "volume": 166841.943018,
  "market_type": "max_temperature",
  "temperature_metric": "high",
  "all_outcomes": [
    {
      "market_id": "2350812",
      "question": "Will the highest temperature in Shanghai be 22°C or below on May 27?",
      "bucket_low": -999.0,
      "bucket_high": 22.0,
      "unit": "C",
      "yes_price": 0.0,
      "no_price": 1.0,
      "volume": 2243.8165,
      "liquidity": null,
      "token_id": "58315418052246153124229548198766083255023621428583154150334447894313478498607",
      "outcomes": [
        "Yes",
        "No"
      ],
      "outcome_prices": [
        0.0,
        1.0
      ],
      "active": true,
      "closed": true,
      "raw_source": {
        "market_slug": "highest-temperature-in-shanghai-on-may-27-2026-22corbelow",
        "condition_id": "0xae851c6cf74102ad038ec9f238f805b27e76b4468a56de7a95550cd3fb024f21"
      }
    },
    {
      "market_id": "2350813",
      "question": "Will the highest temperature in Shanghai be 23°C on May 27?",
      "bucket_low": 23.0,
      "bucket_high": 23.0,
      "unit": "C",
      "yes_price": 0.0,
      "no_price": 1.0,
      "volume": 2049.076081,
      "liquidity": null,
      "token_id": "30171645248584418384950009568645831695412931114306290627773689841519831506878",
      "outcomes": [
        "Yes",
        "No"
      ],
      "outcome_prices": [
        0.0,
        1.0
      ],
      "active": true,
      "closed": true,
      "raw_source": {
        "market_slug": "highest-temperature-in-shanghai-on-may-27-2026-23c",
        "condition_id": "0xd26836d3b0bcbb6308ee147e924e17fd22055ba4c801f2fdae7a0e9ec03e0343"
      }
    },
    {
      "market_id": "2350814",
      "question": "Will the highest temperature in Shanghai be 24°C on May 27?",
      "bucket_low": 24.0,
      "bucket_high": 24.0,
      "unit": "C",
      "yes_price": 0.0,
      "no_price": 1.0,
      "volume": 2919.7322959999997,
      "liquidity": null,
      "token_id": "105426454446789438126507668215608220671608888543211310014528260308402782806332",
      "outcomes": [
        "Yes",
        "No"
      ],
      "outcome_prices": [
        0.0,
        1.0
      ],
      "active": true,
      "closed": true,
      "raw_source": {
        "market_slug": "highest-temperature-in-shanghai-on-may-27-2026-24c",
        "condition_id": "0xbbd7183ac4158c2e9042c42b89ff60f53ceebf1502af90916bfe0d199a8ebc2f"
      }
    },
    {
      "market_id": "2350815",
      "question": "Will the highest temperature in Shanghai be 25°C on May 27?",
      "bucket_low": 25.0,
      "bucket_high": 25.0,
      "unit": "C",
      "yes_price": 0.0,
      "no_price": 1.0,
      "volume": 5302.838307999999,
      "liquidity": null,
      "token_id": "71552676133048969469179758037712800975804361090502805726138598708871418003858",
      "outcomes": [
        "Yes",
        "No"
      ],
      "outcome_prices": [
        0.0,
        1.0
      ],
      "active": true,
      "closed": true,
      "raw_source": {
        "market_slug": "highest-temperature-in-shanghai-on-may-27-2026-25c",
        "condition_id": "0xa6887f5b951bc9f761137329010aa5af7f18813301cab247b9342be9b2f86e0d"
      }
    },
    {
      "market_id": "2350816",
      "question": "Will the highest temperature in Shanghai be 26°C on May 27?",
      "bucket_low": 26.0,
      "bucket_high": 26.0,
      "unit": "C",
      "yes_price": 0.0,
      "no_price": 1.0,
      "volume": 16850.739372999993,
      "liquidity": null,
      "token_id": "13294175850278983786513018749400581407508601922561327531148185585355594831035",
      "outcomes": [
        "Yes",
        "No"
      ],
      "outcome_prices": [
        0.0,
        1.0
      ],
      "active": true,
      "closed": true,
      "raw_source": {
        "market_slug": "highest-temperature-in-shanghai-on-may-27-2026-26c",
        "condition_id": "0x0403863973920c62f10cfaf091867f930747292e1e31a12625f392dac5408efa"
      }
    },
    {
      "market_id": "2350817",
      "question": "Will the highest temperature in Shanghai be 27°C on May 27?",
      "bucket_low": 27.0,
      "bucket_high": 27.0,
      "unit": "C",
      "yes_price": 0.0,
      "no_price": 1.0,
      "volume": 12879.342416000001,
      "liquidity": null,
      "token_id": "75194275772980983215604190553765343915028073045217988102909794395425307014215",
      "outcomes": [
        "Yes",
        "No"
      ],
      "outcome_prices": [
        0.0,
        1.0
      ],
      "active": true,
      "closed": true,
      "raw_source": {
        "market_slug": "highest-temperature-in-shanghai-on-may-27-2026-27c",
        "condition_id": "0xfa1f2095c4084df90df8b8620d6b94cbc08d43427a98c9657dd1e95c23414ca0"
      }
    },
    {
      "market_id": "2350818",
      "question": "Will the highest temperature in Shanghai be 28°C on May 27?",
      "bucket_low": 28.0,
      "bucket_high": 28.0,
      "unit": "C",
      "yes_price": 0.0,
      "no_price": 1.0,
      "volume": 23680.268346,
      "liquidity": null,
      "token_id": "98788066321315896754562422824378800351244568110367157937931614868555071308919",
      "outcomes": [
        "Yes",
        "No"
      ],
      "outcome_prices": [
        0.0,
        1.0
      ],
      "active": true,
      "closed": true,
      "raw_source": {
        "market_slug": "highest-temperature-in-shanghai-on-may-27-2026-28c",
        "condition_id": "0x795e3ad4de9e06627a96bb20ff99fbbb72cb77030669b382eee3e388ecd04670"
      }
    },
    {
      "market_id": "2350819",
      "question": "Will the highest temperature in Shanghai be 29°C on May 27?",
      "bucket_low": 29.0,
      "bucket_high": 29.0,
      "unit": "C",
      "yes_price": 0.0,
      "no_price": 1.0,
      "volume": 14694.410487000006,
      "liquidity": null,
      "token_id": "16132071631357796409417229801103204640205737394671673984611117633482653929937",
      "outcomes": [
        "Yes",
        "No"
      ],
      "outcome_prices": [
        0.0,
        1.0
      ],
      "active": true,
      "closed": true,
      "raw_source": {
        "market_slug": "highest-temperature-in-shanghai-on-may-27-2026-29c",
        "condition_id": "0xdae8561314b24ddb6b1d48b0d1d72cba9fb186b63016fa2df86909a7731ac34d"
      }
    },
    {
      "market_id": "2350820",
      "question": "Will the highest temperature in Shanghai be 30°C on May 27?",
      "bucket_low": 30.0,
      "bucket_high": 30.0,
      "unit": "C",
      "yes_price": 1.0,
      "no_price": 0.0,
      "volume": 37382.42878599999,
      "liquidity": null,
      "token_id": "78576813224698712223154474802354045866714275290411088645589286350570484089296",
      "outcomes": [
        "Yes",
        "No"
      ],
      "outcome_prices": [
        1.0,
        0.0
      ],
      "active": true,
      "closed": true,
      "raw_source": {
        "market_slug": "highest-temperature-in-shanghai-on-may-27-2026-30c",
        "condition_id": "0xc974dd1e6a312ad55ed24616ea226522dc2769f1f07c34e895d69f590870e363"
      }
    },
    {
      "market_id": "2350821",
      "question": "Will the highest temperature in Shanghai be 31°C on May 27?",
      "bucket_low": 31.0,
      "bucket_high": 31.0,
      "unit": "C",
      "yes_price": 0.0,
      "no_price": 1.0,
      "volume": 30409.94278200001,
      "liquidity": null,
      "token_id": "88201348170612363810395644288260713201759249196102786205943664690323032716574",
      "outcomes": [
        "Yes",
        "No"
      ],
      "outcome_prices": [
        0.0,
        1.0
      ],
      "active": true,
      "closed": true,
      "raw_source": {
        "market_slug": "highest-temperature-in-shanghai-on-may-27-2026-31c",
        "condition_id": "0x7c82d8c008d74a4c8b3dbe30c440d55406e1a85bd5749348cb7203310f2aa878"
      }
    },
    {
      "market_id": "2350822",
      "question": "Will the highest temperature in Shanghai be 32°C or higher on May 27?",
      "bucket_low": 32.0,
      "bucket_high": 999.0,
      "unit": "C",
      "yes_price": 0.0,
      "no_price": 1.0,
      "volume": 18429.347643,
      "liquidity": null,
      "token_id": "107798326333146293044957615248106611218365527635621516536944336635224417572720",
      "outcomes": [
        "Yes",
        "No"
      ],
      "outcome_prices": [
        0.0,
        1.0
      ],
      "active": true,
      "closed": true,
      "raw_source": {
        "market_slug": "highest-temperature-in-shanghai-on-may-27-2026-32corhigher",
        "condition_id": "0x53d3b345ef137d77d8f9cd3ab434048909d9707b1a8b0c3323fa4dba6c1b80ec"
      }
    }
  ],
  "market_snapshots": [
    {
      "ts": "2026-06-07T16:05:39.813471+00:00",
      "active": true,
      "closed": true,
      "end_date": "2026-05-27T12:00:00Z",
      "liquidity": null,
      "volume": 166841.943018,
      "outcomes_count": 11,
      "top_bucket": "30.0-30.0C",
      "top_price": 1.0,
      "event_title": "Highest temperature in Shanghai on May 27?"
    }
  ],
  "settle_at": "2026-05-27T16:00:00+00:00",
  "hours_to_settle": -264.1,
  "raw_source": {
    "event_slug": "highest-temperature-in-shanghai-on-may-27-2026",
    "event_id": "522322",
    "markets_count": 11,
    "game_start_time": "2026-05-26 16:00:00+00"
  },
  "status": "inactive",
  "discovery_source": "gamma_history_sync",
  "hours_at_discovery": 0.0,
  "first_seen_at": "2026-06-07T16:05:39.813471+00:00",
  "last_seen_at": "2026-06-07T16:05:39.813471+00:00",
  "last_refreshed_at": "2026-06-07T16:05:39.813471+00:00",
  "created_at": "2026-06-07T16:05:39.813471+00:00",
  "updated_at": "2026-06-10T17:17:30.833793+00:00",
  "forecast_snapshots": [],
  "raw_payload_ref": "data\\raw\\gamma_events_raw.json",
  "extensions": {
    "winning_bucket": {
      "winning_bucket": "30C",
      "resolved_value": "30C",
      "resolution_source": null,
      "winning_market_id": "2350820",
      "winning_question": "Will the highest temperature in Shanghai be 30°C on May 27?"
    },
    "gamma_enriched_at": "2026-06-07T16:05:39.814493+00:00"
  },
  "legacy": null
}