{
  "storage_key": "wuhan_2026-04-16_high",
  "event_id": "379811",
  "event_slug": "highest-temperature-in-wuhan-on-april-16-2026",
  "event_title": "Highest temperature in Wuhan on April 16?",
  "city_slug": "wuhan",
  "city_name": "Wuhan",
  "date": "2026-04-16",
  "unit": "C",
  "station": null,
  "category": null,
  "tags": [
    "Weather",
    "Recurring",
    "Hide From New",
    "Daily Temperature",
    "Wuhan",
    "Rewards Automation 50 4.5 50",
    "temperature"
  ],
  "active": true,
  "closed": true,
  "end_date": "2026-04-16T12:00:00Z",
  "event_end_date": "2026-04-16T12:00:00Z",
  "liquidity": null,
  "volume": 348071.06017700006,
  "market_type": "max_temperature",
  "temperature_metric": "high",
  "all_outcomes": [
    {
      "market_id": "1986164",
      "question": "Will the highest temperature in Wuhan be 16°C or below on April 16?",
      "bucket_low": -999.0,
      "bucket_high": 16.0,
      "unit": "C",
      "yes_price": 0.0,
      "no_price": 1.0,
      "volume": 2564.003943,
      "liquidity": null,
      "token_id": "57948967639018869386183653384887000774089403022765775553136082466803933774695",
      "outcomes": [
        "Yes",
        "No"
      ],
      "outcome_prices": [
        0.0,
        1.0
      ],
      "active": true,
      "closed": true,
      "raw_source": {
        "market_slug": "highest-temperature-in-wuhan-on-april-16-2026-16corbelow",
        "condition_id": "0x002808c2705c8757ab980d48a59d8051a41cb891a74de352fa6b91aba5362878"
      }
    },
    {
      "market_id": "1986165",
      "question": "Will the highest temperature in Wuhan be 17°C on April 16?",
      "bucket_low": 17.0,
      "bucket_high": 17.0,
      "unit": "C",
      "yes_price": 0.0,
      "no_price": 1.0,
      "volume": 1234.517349,
      "liquidity": null,
      "token_id": "52684317300555234586905681308675644725772973640934166413428114712706344859439",
      "outcomes": [
        "Yes",
        "No"
      ],
      "outcome_prices": [
        0.0,
        1.0
      ],
      "active": true,
      "closed": true,
      "raw_source": {
        "market_slug": "highest-temperature-in-wuhan-on-april-16-2026-17c",
        "condition_id": "0x1f7ee73bc44ee698f7a35c6a957fc6627d84d11c6bd81dfe16620c685416900e"
      }
    },
    {
      "market_id": "1986166",
      "question": "Will the highest temperature in Wuhan be 18°C on April 16?",
      "bucket_low": 18.0,
      "bucket_high": 18.0,
      "unit": "C",
      "yes_price": 0.0,
      "no_price": 1.0,
      "volume": 2765.792933,
      "liquidity": null,
      "token_id": "110413598391756689402987920295529073699973884703998917938739160651228868005866",
      "outcomes": [
        "Yes",
        "No"
      ],
      "outcome_prices": [
        0.0,
        1.0
      ],
      "active": true,
      "closed": true,
      "raw_source": {
        "market_slug": "highest-temperature-in-wuhan-on-april-16-2026-18c",
        "condition_id": "0x77a8914b09e30b924e4acbd2ee7935febb9690cad86564d597b9d40e7d17e701"
      }
    },
    {
      "market_id": "1986167",
      "question": "Will the highest temperature in Wuhan be 19°C on April 16?",
      "bucket_low": 19.0,
      "bucket_high": 19.0,
      "unit": "C",
      "yes_price": 0.0,
      "no_price": 1.0,
      "volume": 18509.863750999997,
      "liquidity": null,
      "token_id": "85961691782496137615185289523193695820205321302224145400802905206932840221827",
      "outcomes": [
        "Yes",
        "No"
      ],
      "outcome_prices": [
        0.0,
        1.0
      ],
      "active": true,
      "closed": true,
      "raw_source": {
        "market_slug": "highest-temperature-in-wuhan-on-april-16-2026-19c",
        "condition_id": "0x0494d4c3c12848d47b0f0a5c49e65211ebaccfe3df892f24ad937845ecbf4592"
      }
    },
    {
      "market_id": "1986168",
      "question": "Will the highest temperature in Wuhan be 20°C on April 16?",
      "bucket_low": 20.0,
      "bucket_high": 20.0,
      "unit": "C",
      "yes_price": 0.0,
      "no_price": 1.0,
      "volume": 36494.358107,
      "liquidity": null,
      "token_id": "34045950063566613957996372115710757933628531032285248614353776673495754086801",
      "outcomes": [
        "Yes",
        "No"
      ],
      "outcome_prices": [
        0.0,
        1.0
      ],
      "active": true,
      "closed": true,
      "raw_source": {
        "market_slug": "highest-temperature-in-wuhan-on-april-16-2026-20c",
        "condition_id": "0x4e5c6414d64e1a4b52104902350efb08e7adc4e3bc878422038474144db38331"
      }
    },
    {
      "market_id": "1986169",
      "question": "Will the highest temperature in Wuhan be 21°C on April 16?",
      "bucket_low": 21.0,
      "bucket_high": 21.0,
      "unit": "C",
      "yes_price": 0.0,
      "no_price": 1.0,
      "volume": 60347.15454599999,
      "liquidity": null,
      "token_id": "16362017889380991882746268664818296402337621016974879539495673874249187694633",
      "outcomes": [
        "Yes",
        "No"
      ],
      "outcome_prices": [
        0.0,
        1.0
      ],
      "active": true,
      "closed": true,
      "raw_source": {
        "market_slug": "highest-temperature-in-wuhan-on-april-16-2026-21c",
        "condition_id": "0xbf6b7ff272c85e0f398e71b14b7e76e9ce96ccff616f2f5c80bf6bfdd669f4e4"
      }
    },
    {
      "market_id": "1986170",
      "question": "Will the highest temperature in Wuhan be 22°C on April 16?",
      "bucket_low": 22.0,
      "bucket_high": 22.0,
      "unit": "C",
      "yes_price": 0.0,
      "no_price": 1.0,
      "volume": 107854.09349200003,
      "liquidity": null,
      "token_id": "17708430293471817911412520404901685052769072103418548114393461054893758486694",
      "outcomes": [
        "Yes",
        "No"
      ],
      "outcome_prices": [
        0.0,
        1.0
      ],
      "active": true,
      "closed": true,
      "raw_source": {
        "market_slug": "highest-temperature-in-wuhan-on-april-16-2026-22c",
        "condition_id": "0x15e921c0b8ebaa351a8b05be0d4a22b71b926a4ed1d0ba6d53b64e24902b8910"
      }
    },
    {
      "market_id": "1986171",
      "question": "Will the highest temperature in Wuhan be 23°C on April 16?",
      "bucket_low": 23.0,
      "bucket_high": 23.0,
      "unit": "C",
      "yes_price": 1.0,
      "no_price": 0.0,
      "volume": 28369.07577500003,
      "liquidity": null,
      "token_id": "93961803626079074127010565118703578570555720930465485881132806245207657860663",
      "outcomes": [
        "Yes",
        "No"
      ],
      "outcome_prices": [
        1.0,
        0.0
      ],
      "active": true,
      "closed": true,
      "raw_source": {
        "market_slug": "highest-temperature-in-wuhan-on-april-16-2026-23c",
        "condition_id": "0xb3837c27dee5132978ce87b7df8a7c6c1704bcfbd0fb3733164ddd550fc4996e"
      }
    },
    {
      "market_id": "1986172",
      "question": "Will the highest temperature in Wuhan be 24°C on April 16?",
      "bucket_low": 24.0,
      "bucket_high": 24.0,
      "unit": "C",
      "yes_price": 0.0,
      "no_price": 1.0,
      "volume": 77430.189924,
      "liquidity": null,
      "token_id": "18825801450334943025745457321900382025243465407137597064246257714217907327",
      "outcomes": [
        "Yes",
        "No"
      ],
      "outcome_prices": [
        0.0,
        1.0
      ],
      "active": true,
      "closed": true,
      "raw_source": {
        "market_slug": "highest-temperature-in-wuhan-on-april-16-2026-24c",
        "condition_id": "0xaa04eabc6e4033751d87b32fd9285bea193ccc832bd4b6c039c4cecd94e49d46"
      }
    },
    {
      "market_id": "1986173",
      "question": "Will the highest temperature in Wuhan be 25°C on April 16?",
      "bucket_low": 25.0,
      "bucket_high": 25.0,
      "unit": "C",
      "yes_price": 0.0,
      "no_price": 1.0,
      "volume": 7837.644915,
      "liquidity": null,
      "token_id": "38781554974102157906869688128918726160642204990952727181052561474833076720575",
      "outcomes": [
        "Yes",
        "No"
      ],
      "outcome_prices": [
        0.0,
        1.0
      ],
      "active": true,
      "closed": true,
      "raw_source": {
        "market_slug": "highest-temperature-in-wuhan-on-april-16-2026-25c",
        "condition_id": "0x1e5766b0f91d2d95d11c33838298e235fdf10b5b3c7f186012ceb541c5b06c16"
      }
    },
    {
      "market_id": "1986174",
      "question": "Will the highest temperature in Wuhan be 26°C or higher on April 16?",
      "bucket_low": 26.0,
      "bucket_high": 999.0,
      "unit": "C",
      "yes_price": 0.0,
      "no_price": 1.0,
      "volume": 4664.365442000002,
      "liquidity": null,
      "token_id": "103267476538075348625527845843592681364391275780352942206294456145053968355771",
      "outcomes": [
        "Yes",
        "No"
      ],
      "outcome_prices": [
        0.0,
        1.0
      ],
      "active": true,
      "closed": true,
      "raw_source": {
        "market_slug": "highest-temperature-in-wuhan-on-april-16-2026-26corhigher",
        "condition_id": "0x0dbb0f234fb62d1c824f3f21bfb58870bee7e9dfa7e58737cd579dde2bf75fbd"
      }
    }
  ],
  "market_snapshots": [
    {
      "ts": "2026-06-07T16:06:05.826177+00:00",
      "active": true,
      "closed": true,
      "end_date": "2026-04-16T12:00:00Z",
      "liquidity": null,
      "volume": 348071.06017700006,
      "outcomes_count": 11,
      "top_bucket": "23.0-23.0C",
      "top_price": 1.0,
      "event_title": "Highest temperature in Wuhan on April 16?"
    }
  ],
  "settle_at": "2026-04-16T16:00:00+00:00",
  "hours_to_settle": -1248.1,
  "raw_source": {
    "event_slug": "highest-temperature-in-wuhan-on-april-16-2026",
    "event_id": "379811",
    "markets_count": 11,
    "game_start_time": "2026-04-15 16:00:00+00"
  },
  "status": "inactive",
  "discovery_source": "gamma_history_sync",
  "hours_at_discovery": 0.0,
  "first_seen_at": "2026-06-07T16:06:05.826177+00:00",
  "last_seen_at": "2026-06-07T16:06:05.826177+00:00",
  "last_refreshed_at": "2026-06-07T16:06:05.826177+00:00",
  "created_at": "2026-06-07T16:06:05.826177+00:00",
  "updated_at": "2026-06-10T17:17:31.411203+00:00",
  "forecast_snapshots": [],
  "raw_payload_ref": "data\\raw\\gamma_events_raw.json",
  "extensions": {
    "winning_bucket": {
      "winning_bucket": "23C",
      "resolved_value": "23C",
      "resolution_source": null,
      "winning_market_id": "1986171",
      "winning_question": "Will the highest temperature in Wuhan be 23°C on April 16?"
    },
    "gamma_enriched_at": "2026-06-07T16:06:05.827182+00:00"
  },
  "legacy": null
}